duel/__init__.py
duel/__main__.py
duel/audioEngine.py
duel/camera.py
duel/desolateDesertMap.py
duel/gameEngine.py
duel/gameFrame.py
duel/mainMenuFrame.py
duel/map.py
duel/mapSelectionList.py
duel/menuButtons.py
duel/pauseButtons.py
duel/player.py
duel/playerSkinsList.py
duel/redForestMap.py
duel/sword.py
duel/swordHitBoxes.py
duel/tile.py
duel/window.py
duel/Resources/Lobster.ttf
duel/Resources/desolateDesertMap.txt
duel/Resources/redForestMap.txt
duel/Resources/Images/BetterSwordSizeMaybe.png
duel/Resources/Images/CreditsSplashScreen.png
duel/Resources/Images/DesolateDesertBG.png
duel/Resources/Images/DesolateDesertSpike.png
duel/Resources/Images/DesolateDesertTile.png
duel/Resources/Images/Flag.png
duel/Resources/Images/Image.png
duel/Resources/Images/KingArthurDeath1L.png
duel/Resources/Images/KingArthurDeath1R.png
duel/Resources/Images/KingArthurDeath2L.png
duel/Resources/Images/KingArthurDeath2R.png
duel/Resources/Images/KingArthurDeath3L.png
duel/Resources/Images/KingArthurDeath3R.png
duel/Resources/Images/KingArthurDuckL.png
duel/Resources/Images/KingArthurDuckL_nosword.png
duel/Resources/Images/KingArthurDuckR.png
duel/Resources/Images/KingArthurDuckR_nosword.png
duel/Resources/Images/KingArthurFlag.png
duel/Resources/Images/KingArthurGhostDeath1L.png
duel/Resources/Images/KingArthurGhostDeath1R.png
duel/Resources/Images/KingArthurGhostDeath2L.png
duel/Resources/Images/KingArthurGhostDeath2R.png
duel/Resources/Images/KingArthurGhostDeath3L.png
duel/Resources/Images/KingArthurGhostDeath3R.png
duel/Resources/Images/KingArthurGhostDuckL.png
duel/Resources/Images/KingArthurGhostDuckL_nosword.png
duel/Resources/Images/KingArthurGhostDuckR.png
duel/Resources/Images/KingArthurGhostDuckR_nosword.png
duel/Resources/Images/KingArthurGhostHighL.png
duel/Resources/Images/KingArthurGhostHighL_nosword.png
duel/Resources/Images/KingArthurGhostHighR.png
duel/Resources/Images/KingArthurGhostHighR_nosword.png
duel/Resources/Images/KingArthurGhostHighThrustL.png
duel-3.6.dist-info/LICENSE.txt
duel-3.6.dist-info/METADATA
duel-3.6.dist-info/WHEEL
duel-3.6.dist-info/entry_points.txt
duel-3.6.dist-info/top_level.txt
duel-3.6.dist-info/RECORD
