Metadata-Version: 2.1
Name: duel
Version: 3.6
Summary: Locally Multiplayer Dueling game
Home-page: https://github.com/AlexisDougherty13/Duel
Author: Pythson Buds
Author-email: zachary.s1110@gmail.com
License: MIT
Platform: UNKNOWN
Classifier: License :: OSI Approved :: MIT License
Classifier: Programming Language :: Python :: 3
Classifier: Programming Language :: Python :: 3.8
Requires-Dist: pygame (==2.0.0.dev10)
